mdx_attr_cols.py
mdx_attr_cols-0.1.1.dist-info/RECORD
mdx_attr_cols-0.1.1.dist-info/METADATA
mdx_attr_cols-0.1.1.dist-info/DESCRIPTION.rst
mdx_attr_cols-0.1.1.dist-info/top_level.txt
mdx_attr_cols-0.1.1.dist-info/metadata.json
mdx_attr_cols-0.1.1.dist-info/WHEEL
