Metadata-Version: 2.0
Name: mdx-attr-cols
Version: 0.1.1
Summary: A bootstrap 3 row and columns extension for Markdown
Home-page: http://github.com/CTPUG/mdx_attr_cols
Author: CTPUG
Author-email: ctpug@googlegroups.com
License: MIT
Platform: UNKNOWN
Classifier: Development Status :: 4 - Beta
Classifier: Intended Audience :: Developers
Classifier: License :: OSI Approved :: MIT License
Classifier: Operating System :: POSIX
Classifier: Programming Language :: Python
Classifier: Programming Language :: Python :: 2.7
Classifier: Programming Language :: Python :: 3
Classifier: Programming Language :: Python :: 3.3
Classifier: Programming Language :: Python :: 3.4
Classifier: Framework :: Django
Classifier: Topic :: Software Development :: Libraries :: Python Modules
Classifier: Topic :: Internet :: WWW/HTTP
Requires-Dist: markdown
Requires-Dist: mdx-outline
